<included>
    <appender name="SYSTEM_FILE" class="ch.qos.logback.core.rolling.RollingFileAppender">
        <file>${SYSTEM_LOG_FILE}</file>
        <rollingPolicy class="ch.qos.logback.core.rolling.SizeAndTimeBasedRollingPolicy">
            <fileNamePattern>${SYSTEM_LOG_FILE}.%d{yyyy-MM-dd}.%i.gz</fileNamePattern>
            <maxFileSize>10MB</maxFileSize>
            <maxHistory>30</maxHistory>
            <totalSizeCap>3GB</totalSizeCap>
        </rollingPolicy>
        <encoder>
            <pattern>${FILE_LOG_PATTERN}</pattern>
        </encoder>
    </appender>
</included>
